onnx/onnx-ml.proto
onnx/tools/net_drawer.py
onnx/tools/__init__.py
onnx/onnx.proto
onnx/mapping.py
onnx/frontend/__init__.py
onnx/onnx-operators.in.proto
onnx/checker.cc
onnx/numpy_helper.py
onnx/onnx_pb.h
onnx/proto_utils.h
onnx/onnx-operators.proto
onnx/onnx-operators-ml.proto
onnx/bin/__init__.py
onnx/bin/checker.py
onnx/version.py
onnx/gen_proto.py
onnx/onnx.in.proto
onnx/onnxifi.h
onnx/onnx_pb.py
onnx/common/assertions.h
onnx/common/assertions.cc
onnx/common/ir.h
onnx/common/stl_backports.h
onnx/common/ir_pb_converter.cc
onnx/common/tensor.h
onnx/common/status.cc
onnx/common/constants.h
onnx/common/ir_pb_converter.h
onnx/common/status.h
onnx/common/array_ref.h
onnx/common/interned_strings.h
onnx/common/interned_strings.cc
onnx/common/graph_node_list.h
onnx/test/c++/op_reg_test.cc
onnx/test/c++/test_main.cc
onnx/__init__.py
onnx/.libs/libprotobuf-024eded0.so.9.0.1
onnx/onnx-operators_pb.h
onnx/checker.h
onnx/helper.py
onnx/string_utils.h
onnx/onnx_ONNX_REL_1_3_ml_pb2.py
onnx/onnx_operators_pb.py
onnx/shape_inference.py
onnx/onnx_operators_ONNX_REL_1_3_ml_pb2.py
onnx/backend/test/report/__init__.py
onnx/backend/test/report/base.py
onnx/backend/test/report/coverage.py
onnx/backend/test/data/pytorch-converted/test_ELU/model.onnx
onnx/backend/test/data/pytorch-converted/test_ELU/test_data_set_0/output_0.pb
onnx/backend/test/data/pytorch-converted/test_ELU/test_data_set_0/input_0.pb
onnx/backend/test/data/pytorch-converted/test_Conv2d_depthwise_strided/model.onnx
onnx/backend/test/data/pytorch-converted/test_Conv2d_depthwise_strided/test_data_set_0/output_0.pb
onnx/backend/test/data/pytorch-converted/test_Conv2d_depthwise_strided/test_data_set_0/input_0.pb
onnx/backend/test/data/pytorch-converted/test_ConvTranspose2d/model.onnx
onnx/backend/test/data/pytorch-converted/test_ConvTranspose2d/test_data_set_0/output_0.pb
onnx/backend/test/data/pytorch-converted/test_ConvTranspose2d/test_data_set_0/input_0.pb
onnx-1.2.3.dist-info/entry_points.txt
onnx-1.2.3.dist-info/WHEEL
onnx-1.2.3.dist-info/RECORD
onnx-1.2.3.dist-info/METADATA
onnx-1.2.3.dist-info/top_level.txt
onnx-1.2.3.dist-info/LICENSE.txt
