Metadata-Version: 1.0
Name: onnx
Version: 1.2.3
Summary: Open Neural Network Exchange
Home-page: https://github.com/onnx/onnx
Author: bddppq
Author-email: jbai@fb.com
License: UNKNOWN
Platform: UNKNOWN
